LICENSE
README.md
setup.py
src/sentry_for_wxwork.egg-info/PKG-INFO
src/sentry_for_wxwork.egg-info/SOURCES.txt
src/sentry_for_wxwork.egg-info/dependency_links.txt
src/sentry_for_wxwork.egg-info/entry_points.txt
src/sentry_for_wxwork.egg-info/not-zip-safe
src/sentry_for_wxwork.egg-info/requires.txt
src/sentry_for_wxwork.egg-info/top_level.txt
src/sentry_wxwork/__init__.py
src/sentry_wxwork/forms.py
src/sentry_wxwork/plugin.py