Metadata-Version: 2.1
Name: sentry-for-wxwork
Version: 1.1.0
Summary: A Sentry extension which send errors stats to WxWork
Home-page: https://github.com/liangxg787/sentry-for-wxwork
Author: Ngenie
Author-email: hplxg@hotmail.com
License: MIT
Keywords: sentry wxwork
Platform: UNKNOWN
Classifier: Programming Language :: Python :: 2.7
Classifier: License :: OSI Approved :: MIT License
License-File: LICENSE
